{"id":22,"seller":{"id":0,"name":"MyCompany","taxpayerIdentificationNumber":"12345"},"buyer":{"id":0,"name":"buyer","taxpayerIdentificationNumber":"666"},"entries":[{"description":"zielony groszek","vatRate":20,"amount":10,"vatAmount":2},{"description":"orzechy wloskie","vatRate":20,"amount":90,"vatAmount":18}],"amount":100,"vatAmount":20,"localDate":"2017-10-18"}
{"id":23,"seller":{"id":0,"name":"MyCompany","taxpayerIdentificationNumber":"12345"},"buyer":{"id":0,"name":"buyer","taxpayerIdentificationNumber":"666"},"entries":[{"description":"zielony groszek","vatRate":20,"amount":10,"vatAmount":2},{"description":"orzechy wloskie","vatRate":20,"amount":90,"vatAmount":18}],"amount":100,"vatAmount":20,"localDate":"2017-10-17"}
{"id":24,"seller":{"id":0,"name":"MyCompany","taxpayerIdentificationNumber":"12345"},"buyer":{"id":0,"name":"buyer","taxpayerIdentificationNumber":"666"},"entries":[{"description":"zielony groszek","vatRate":20,"amount":10,"vatAmount":2},{"description":"orzechy wloskie","vatRate":20,"amount":90,"vatAmount":18}],"amount":100,"vatAmount":20,"localDate":"2017-10-17"}
{"id":25,"seller":{"id":0,"name":"MyCompany","taxpayerIdentificationNumber":"12345"},"buyer":{"id":0,"name":"buyer","taxpayerIdentificationNumber":"666"},"entries":[{"description":"zielony groszek","vatRate":20,"amount":10,"vatAmount":2},{"description":"orzechy wloskie","vatRate":20,"amount":90,"vatAmount":18}],"amount":100,"vatAmount":20,"localDate":"2017-10-16"}
{"id":26,"seller":{"id":0,"name":"MyCompany","taxpayerIdentificationNumber":"12345"},"buyer":{"id":0,"name":"buyer","taxpayerIdentificationNumber":"666"},"entries":[{"description":"zielony groszek","vatRate":20,"amount":10,"vatAmount":2},{"description":"orzechy wloskie","vatRate":20,"amount":90,"vatAmount":18}],"amount":100,"vatAmount":20,"localDate":"2017-10-15"}
{"id":27,"seller":{"id":0,"name":"asdf","taxpayerIdentificationNumber":"12345"},"buyer":{"id":0,"name":"buyer","taxpayerIdentificationNumber":"666"},"entries":[{"description":"zielony groszek","vatRate":20,"amount":10,"vatAmount":2},{"description":"orzechy wloskie","vatRate":20,"amount":90,"vatAmount":18}],"amount":100,"vatAmount":20,"localDate":"2017-10-15"}
{"id":28,"seller":{"id":0,"name":"asdf","taxpayerIdentificationNumber":"12345"},"buyer":{"id":0,"name":"buyer","taxpayerIdentificationNumber":"666"},"entries":[{"description":"zielony groszek","vatRate":20,"amount":10,"vatAmount":2},{"description":"orzechy wloskie","vatRate":20,"amount":90,"vatAmount":18}],"amount":100,"vatAmount":20,"localDate":"2017-10-15"}
{"id":29,"seller":{"id":0,"name":"asdf","taxpayerIdentificationNumber":"12345"},"buyer":{"id":0,"name":"buyer","taxpayerIdentificationNumber":"666"},"entries":[{"description":"zielony groszek","vatRate":20,"amount":10,"vatAmount":2},{"description":"orzechy wloskie","vatRate":20,"amount":90,"vatAmount":18}],"amount":100,"vatAmount":20,"localDate":"2017-10-15"}
{"id":30,"seller":{"id":0,"name":"asdf","taxpayerIdentificationNumber":"12345"},"buyer":{"id":0,"name":"buyer","taxpayerIdentificationNumber":"666"},"entries":[{"description":"zielony groszek","vatRate":20,"amount":10,"vatAmount":2},{"description":"orzechy wloskie","vatRate":20,"amount":90,"vatAmount":18}],"amount":100,"vatAmount":20,"localDate":"2017-10-15"}
